vectorwave/__init__.py
vectorwave/batch/__init__.py
vectorwave/batch/batch.py
vectorwave/core/__init__.py
vectorwave/core/auto_injector.py
vectorwave/core/core.py
vectorwave/core/decorator.py
vectorwave/core/generator.py
vectorwave/core/llm/__init__.py
vectorwave/core/llm/base.py
vectorwave/core/llm/factory.py
vectorwave/core/llm/openai_client.py
vectorwave/database/__init__.py
vectorwave/database/archiver.py
vectorwave/database/dataset.py
vectorwave/database/db.py
vectorwave/database/db_search.py
vectorwave/exception/__init__.py
vectorwave/exception/exceptions.py
vectorwave/models/__init__.py
vectorwave/models/db_config.py
vectorwave/monitoring/__init__.py
vectorwave/monitoring/alert/__init__.py
vectorwave/monitoring/alert/base.py
vectorwave/monitoring/alert/factory.py
vectorwave/monitoring/alert/null_alerter.py
vectorwave/monitoring/alert/webhook_alerter.py
vectorwave/monitoring/monitoring.py
vectorwave/monitoring/tracer.py
vectorwave/prediction/__init__.py
vectorwave/prediction/predictor.py
vectorwave/search/__init__.py
vectorwave/search/execution_search.py
vectorwave/search/extended_search.py
vectorwave/search/rag_search.py
vectorwave/utils/__init__.py
vectorwave/utils/context.py
vectorwave/utils/function_cache.py
vectorwave/utils/healer.py
vectorwave/utils/replayer.py
vectorwave/utils/replayer_semantic.py
vectorwave/utils/return_caching_utils.py
vectorwave/utils/status.py
vectorwave/vectorizer/__init__.py
vectorwave/vectorizer/base.py
vectorwave/vectorizer/factory.py
vectorwave/vectorizer/huggingface_vectorizer.py
vectorwave/vectorizer/openai_vectorizer.py
vectorwave/vectorwave_core.cpython-38-x86_64-linux-gnu.so
vectorwave-0.2.8.dist-info/METADATA
vectorwave-0.2.8.dist-info/WHEEL
vectorwave-0.2.8.dist-info/licenses/LICENSE
vectorwave-0.2.8.dist-info/licenses/NOTICE
vectorwave-0.2.8.dist-info/RECORD
