Metadata-Version: 2.4
Name: vectorwave
Version: 0.2.8
Classifier: Programming Language :: Python :: 3
Classifier: Programming Language :: Python :: 3.10
Classifier: Programming Language :: Python :: 3.11
Classifier: Programming Language :: Python :: 3.12
Classifier: Programming Language :: Python :: 3.13
Classifier: Programming Language :: Rust
Classifier: Operating System :: OS Independent
Classifier: Development Status :: 3 - Alpha
Classifier: Intended Audience :: Developers
Requires-Dist: weaviate-client>=4.0.0
Requires-Dist: pydantic-settings>=2.0.0
Requires-Dist: sentence-transformers
Requires-Dist: requests
Requires-Dist: openai
License-File: LICENSE
License-File: NOTICE
Summary: VectorWave: Seamless Auto-Vectorization Framework
Author-email: junyeonggim <junyeonggim5@gmail.com>
License-Expression: MIT
Requires-Python: >=3.10
Project-URL: Repository, https://github.com/cozymori/vectorwave
